dash_defer_js_import
