Metadata-Version: 2.1
Name: dash-defer-js-import
Version: 0.0.2
Summary: Deferring loading of JS files until after React loads
Home-page: UNKNOWN
Author: zouhair zouhair.mahboubi@gmail.com
License: MIT
Platform: UNKNOWN
